pum_def_9_1/__init__.py
pum_def_9_1/binary.py
pum_def_9_1/converters.py
pum_def_9_1/error_check.py
pum_def_9_1/linear.py
pum_def_9_1/sort.py
pum_def_9_1-0.1.6.dist-info/METADATA
pum_def_9_1-0.1.6.dist-info/WHEEL
pum_def_9_1-0.1.6.dist-info/top_level.txt
pum_def_9_1-0.1.6.dist-info/RECORD
