Metadata-Version: 2.1
Name: pum-def-9-1
Version: 0.1.6
Summary: Все необходимые команды для уроков информатики в 9 классе 2023-2024 года обучения. *Сделано учеником ПУМа
Author: USEK
Classifier: Programming Language :: Python :: 3.10
Classifier: License :: OSI Approved :: MIT License
Classifier: Operating System :: OS Independent
Requires-Python: >=3.7
